purview_py/__init__.py
purview_py/auth/BasicAuth.py
purview_py/auth/TokenAuth.py
purview_py/auth/__init__.py
purview_py/conn/Connection.py
purview_py/conn/__init__.py
purview_py/controller/Controller.py
purview_py/controller/__init__.py
purview_py/controller/entity/PurviewEntity.py
purview_py/controller/entity/__init__.py
purview_py/controller/type/Attribute.py
purview_py/controller/type/PurviewType.py
purview_py/controller/type/__init__.py
purview_py-0.0.10.dist-info/LICENCE
purview_py-0.0.10.dist-info/METADATA
purview_py-0.0.10.dist-info/WHEEL
purview_py-0.0.10.dist-info/top_level.txt
purview_py-0.0.10.dist-info/RECORD
