Metadata-Version: 2.1
Name: purview-py
Version: 0.0.10
Summary: Python wrapper for MSFT Purview and Apache Atlas APIs
Home-page: https://github.com/spydernaz/purview_py
Author: Nathaniel Vala
Author-email: nathanielvala@hotmail.com
License: MIT
Keywords: API,Data Management,Purview,Apache,Atlas,Metadata
Platform: UNKNOWN
Classifier: Development Status :: 3 - Alpha
Classifier: Intended Audience :: Developers
Classifier: Topic :: Software Development :: Build Tools
Classifier: License :: OSI Approved :: MIT License
Classifier: Programming Language :: Python :: 3
Classifier: Programming Language :: Python :: 3.4
Classifier: Programming Language :: Python :: 3.5
Classifier: Programming Language :: Python :: 3.6
Classifier: Programming Language :: Python :: 3.7
Classifier: Programming Language :: Python :: 3.8
Classifier: Programming Language :: Python :: 3.9
Requires-Python: >=3.6
License-File: LICENCE
Requires-Dist: requests
